bohri_calendar/__init__.py
bohri_calendar/calendar_converter.py
bohri_calendar/cli.py
bohri_calendar/pdf_generator.py
src/__init__.py
src/calendar_converter.py
src/cli.py
src/pdf_generator.py
bohri_calendar-0.1.0.dist-info/METADATA
bohri_calendar-0.1.0.dist-info/WHEEL
bohri_calendar-0.1.0.dist-info/entry_points.txt
bohri_calendar-0.1.0.dist-info/top_level.txt
bohri_calendar-0.1.0.dist-info/RECORD
