Metadata-Version: 2.1
Name: bohri_calendar
Version: 0.1.0
Summary: A tool for generating Bohri calendar PDFs
Author: Yusuf Sabuwala
Author-email: yusuff.0279@gmail.com
Requires-Dist: playwright
Requires-Dist: Pillow
Requires-Dist: reportlab
Requires-Dist: asyncio
